[
    {
        "Name": "USDC",
        "Status": "-",
        "Number": "51300",
        "Value": "51300",
        "GT": "-",
        "OPIUM": "-",
        "Instrument": "0"
    },
    {
        "Name": "uni.FTSE",
        "Status": "-",
        "Number": "1000",
        "Value": "1000",
        "GT": "100",
        "OPIUM": "1500",
        "Instrument": "0"
    },
    {
        "Name": "uni.CCIV",
        "Status": "-",
        "Number": "10000",
        "Value": "100000",
        "GT": "100",
        "OPIUM": "1500",
        "Instrument": "0"
    },
    {
        "Name": "uni.FTSE",
        "Status": "stake",
        "Number": "1000",
        "Value": "1000",
        "GT": "5",
        "OPIUM": "3000",
        "Instrument": "0"
    },
    {
        "Name": "uni.FTSE",
        "Status": "pool",
        "Number": "1000",
        "Value": "1000",
        "GT": "10",
        "OPIUM": "1000",
        "Instrument": "0"
    },
    {
        "Name": "GT",
        "Status": "-",
        "Number": "10000",
        "Value": "1000",
        "GT": "-",
        "OPIUM": "-",
        "Instrument": "0"
    },
    {
        "Name": "UMA",
        "Status": "-",
        "Number": "5000",
        "Value": "5000",
        "GT": "-",
        "OPIUM": "-",
        "Instrument": "0"
    }
]
